demand_model/__init__.py
demand_model/base.py
demand_model/multinomial/__init__.py
demand_model/multinomial/predictor.py
demand_model/multinomial/utils.py
demand_model/stock_and_flow/__init__.py
demand_model/stock_and_flow/predictor.py
demand_model/stock_and_flow/transitions.py
demand_model-0.2.0.dist-info/LICENSE
demand_model-0.2.0.dist-info/METADATA
demand_model-0.2.0.dist-info/WHEEL
demand_model-0.2.0.dist-info/entry_points.txt
demand_model-0.2.0.dist-info/RECORD
