Metadata-Version: 2.1
Name: demand-model
Version: 0.2.0
Summary: Social Finance demand model predictor
Author: dezog
Requires-Python: >=3.10,<4.0
Classifier: Programming Language :: Python :: 3
Classifier: Programming Language :: Python :: 3.10
Classifier: Programming Language :: Python :: 3.11
Classifier: Programming Language :: Python :: 3.12
Provides-Extra: cli
Provides-Extra: jupyter
Provides-Extra: pyodide
Requires-Dist: PyYAML (>=6.0,<7.0)
Requires-Dist: click (>=8.1.3,<9.0.0)
Requires-Dist: fs (>=2.4.16,<3.0.0)
Requires-Dist: jupyterlab (>=3.6.7,<4.0.0) ; extra == "jupyter"
Requires-Dist: matplotlib (>=3.5.2,<4.0.0) ; extra == "cli" or extra == "jupyter"
Requires-Dist: numpy (>=1.22.4,<2.0.0)
Requires-Dist: openpyxl (>=3.0.10,<4.0.0) ; extra == "cli" or extra == "jupyter" or extra == "pyodide"
Requires-Dist: pandas (>=1.4.2,<2.0.0)
Requires-Dist: plotly (>=5.11.0,<6.0.0) ; extra == "jupyter" or extra == "pyodide"
Requires-Dist: python-dateutil (>=2.8.2,<3.0.0)
Requires-Dist: tqdm (>=4.64.1,<5.0.0) ; extra == "cli" or extra == "jupyter"
